<?xml version="1.0" encoding="ISO-8859-1"?>

<xport>
  <meta>
    <start>1406980800</start>
    <step>2160</step>
    <end>1406980800</end>
    <rows>81</rows>
    <columns>1</columns>
    <legend>
      <entry>Temperatura de CPU</entry>
    </legend>
  </meta>
  <data>
    <row><t>1406980800</t><v>3.5589370689e+01</v></row>
    <row><t>1406982960</t><v>3.5791963730e+01</v></row>
    <row><t>1406985120</t><v>3.8806031231e+01</v></row>
    <row><t>1406987280</t><v>4.0008755631e+01</v></row>
    <row><t>1406989440</t><v>4.0272258568e+01</v></row>
    <row><t>1406991600</t><v>4.1044720023e+01</v></row>
    <row><t>1406993760</t><v>4.1809239843e+01</v></row>
    <row><t>1406995920</t><v>4.0676928722e+01</v></row>
    <row><t>1406998080</t><v>4.0412207485e+01</v></row>
    <row><t>1407000240</t><v>4.0954590698e+01</v></row>
    <row><t>1407002400</t><v>4.2272789469e+01</v></row>
    <row><t>1407004560</t><v>4.2052149881e+01</v></row>
    <row><t>1407006720</t><v>4.0569253008e+01</v></row>
    <row><t>1407008880</t><v>4.1129268773e+01</v></row>
    <row><t>1407011040</t><v>4.1179283306e+01</v></row>
    <row><t>1407013200</t><v>4.1212307990e+01</v></row>
    <row><t>1407015360</t><v>4.1235301839e+01</v></row>
    <row><t>1407017520</t><v>4.1302572994e+01</v></row>
    <row><t>1407019680</t><v>4.1827998342e+01</v></row>
    <row><t>1407021840</t><v>4.2216695812e+01</v></row>
    <row><t>1407024000</t><v>4.2515002795e+01</v></row>
    <row><t>1407026160</t><v>4.1625040252e+01</v></row>
    <row><t>1407028320</t><v>4.1066553799e+01</v></row>
    <row><t>1407030480</t><v>4.1072166296e+01</v></row>
    <row><t>1407032640</t><v>4.0889662515e+01</v></row>
    <row><t>1407034800</t><v>4.0651348542e+01</v></row>
    <row><t>1407036960</t><v>4.0702860328e+01</v></row>
    <row><t>1407039120</t><v>4.0642778319e+01</v></row>
    <row><t>1407041280</t><v>4.0536561515e+01</v></row>
    <row><t>1407043440</t><v>4.0210708951e+01</v></row>
    <row><t>1407045600</t><v>4.0156852252e+01</v></row>
    <row><t>1407047760</t><v>4.0312777655e+01</v></row>
    <row><t>1407049920</t><v>4.0314250501e+01</v></row>
    <row><t>1407052080</t><v>3.9872828461e+01</v></row>
    <row><t>1407054240</t><v>3.8802553531e+01</v></row>
    <row><t>1407056400</t><v>4.0074230738e+01</v></row>
    <row><t>1407058560</t><v>3.9365458201e+01</v></row>
    <row><t>1407060720</t><v>3.8584030383e+01</v></row>
    <row><t>1407062880</t><v>3.6221857833e+01</v></row>
    <row><t>1407065040</t><v>3.4536704609e+01</v></row>
    <row><t>1407067200</t><v>3.8863542572e+01</v></row>
    <row><t>1407069360</t><v>3.2291691230e+01</v></row>
    <row><t>1407071520</t><v>3.1892337378e+01</v></row>
    <row><t>1407073680</t><v>3.1617091797e+01</v></row>
    <row><t>1407075840</t><v>3.1587581736e+01</v></row>
    <row><t>1407078000</t><v>3.2251955721e+01</v></row>
    <row><t>1407080160</t><v>3.6933843108e+01</v></row>
    <row><t>1407082320</t><v>3.5573611963e+01</v></row>
    <row><t>1407084480</t><v>3.6684765812e+01</v></row>
    <row><t>1407086640</t><v>3.7017017507e+01</v></row>
    <row><t>1407088800</t><v>3.7625829545e+01</v></row>
    <row><t>1407090960</t><v>3.8998976934e+01</v></row>
    <row><t>1407093120</t><v>3.5985926303e+01</v></row>
    <row><t>1407095280</t><v>3.5966290131e+01</v></row>
    <row><t>1407097440</t><v>3.5290796326e+01</v></row>
    <row><t>1407099600</t><v>3.3711659173e+01</v></row>
    <row><t>1407101760</t><v>3.4130223889e+01</v></row>
    <row><t>1407103920</t><v>3.9269731170e+01</v></row>
    <row><t>1407106080</t><v>4.0111944589e+01</v></row>
    <row><t>1407108240</t><v>4.1149420396e+01</v></row>
    <row><t>1407110400</t><v>4.2374334342e+01</v></row>
    <row><t>1407112560</t><v>NaN</v></row>
    <row><t>1407114720</t><v>4.4616606931e+01</v></row>
    <row><t>1407116880</t><v>4.4646829591e+01</v></row>
    <row><t>1407119040</t><v>4.4669832644e+01</v></row>
    <row><t>1407121200</t><v>4.4278388344e+01</v></row>
    <row><t>1407123360</t><v>4.3340237219e+01</v></row>
    <row><t>1407125520</t><v>4.3323446365e+01</v></row>
    <row><t>1407127680</t><v>4.3175297792e+01</v></row>
    <row><t>1407129840</t><v>4.3161315209e+01</v></row>
    <row><t>1407132000</t><v>4.2968556663e+01</v></row>
    <row><t>1407134160</t><v>4.2764934406e+01</v></row>
    <row><t>1407136320</t><v>4.2881204533e+01</v></row>
    <row><t>1407138480</t><v>4.3965450093e+01</v></row>
    <row><t>1407140640</t><v>4.4501834911e+01</v></row>
    <row><t>1407142800</t><v>4.4412594837e+01</v></row>
    <row><t>1407144960</t><v>4.4270985026e+01</v></row>
    <row><t>1407147120</t><v>4.2079165321e+01</v></row>
    <row><t>1407149280</t><v>4.2231067477e+01</v></row>
    <row><t>1407151440</t><v>4.1317624543e+01</v></row>
    <row><t>1407153600</t><v>NaN</v></row>
  </data>
</xport>
